{"29587733518804856569": {"username": "lubin", "title": "Hello Greendit !", "text": "Give him a name", "image": "https://i.imgur.com/XHC70hv.png", "upvotes": ["Slaycraft", "lubin"], "downvotes": ["totob12"]}, "88179435790362576015": {"username": "lubin", "title": "Oliver", "text": "WORSHIP HIM", "image": "https://i.imgur.com/4g4r8NY.jpg", "upvotes": ["Slaycraft", "totob12"], "downvotes": []}, "83140747732214450877": {"username": "lubin", "title": "It's been a pleasure", "text": "Have a wonderful day", "image": "https://i.imgur.com/JF8KKkj.png", "upvotes": ["Slaycraft", "totob12"], "downvotes": ["lubin"]}, "54752596401067738613": {"username": "lubin", "title": "...", "text": "yes", "image": "https://i.imgur.com/gcCm03C.png", "upvotes": ["lubin"], "downvotes": ["totob12"]}, "34514916086501441263": {"username": "lubin", "title": "Antonin", "text": "...", "image": "https://i.imgur.com/FrWEUDb.png", "upvotes": ["totob12", "lubin"], "downvotes": []}, "33264241998255122521": {"username": "lubin", "title": "That one username on Greendit", "text": "...", "image": "https://i.imgur.com/O2wokbw.png", "upvotes": ["totob12"], "downvotes": ["lubin"]}}